abalytics/__init__.py
abalytics/analysis.py
abalytics/significance_tests.py
abalytics/utils.py
abalytics-3.0.6.dist-info/LICENSE
abalytics-3.0.6.dist-info/METADATA
abalytics-3.0.6.dist-info/WHEEL
abalytics-3.0.6.dist-info/top_level.txt
abalytics-3.0.6.dist-info/RECORD
