Metadata-Version: 2.1
Name: abalytics
Version: 3.0.6
Summary: Advanced A/B Testing Statistical Analytics
Author: Janis Berneker
License: LICENSE
Project-URL: Repository, https://github.com/BigBerny/abalytics
Requires-Python: >=3.8
License-File: LICENSE
Requires-Dist: pandas >=1.5.2
Requires-Dist: scipy >=1.10.1
Requires-Dist: statsmodels >=0.14.1
Requires-Dist: scikit-posthocs >=0.8.1
Requires-Dist: pingouin >=0.5.4
Requires-Dist: tabulate >=0.9.0
